nonebot/adapters/feishu/__init__.py
nonebot/adapters/feishu/adapter.py
nonebot/adapters/feishu/bot.py
nonebot/adapters/feishu/config.py
nonebot/adapters/feishu/event.py
nonebot/adapters/feishu/exception.py
nonebot/adapters/feishu/message.py
nonebot/adapters/feishu/models/__init__.py
nonebot/adapters/feishu/models/api.py
nonebot/adapters/feishu/models/common.py
nonebot/adapters/feishu/utils.py
nonebot_adapter_feishu-2.6.2.dist-info/LICENSE
nonebot_adapter_feishu-2.6.2.dist-info/METADATA
nonebot_adapter_feishu-2.6.2.dist-info/WHEEL
nonebot_adapter_feishu-2.6.2.dist-info/RECORD
