Metadata-Version: 2.1
Name: nonebot-adapter-feishu
Version: 2.6.2
Summary: feishu(larksuite) adapter for nonebot2
Home-page: https://feishu.adapters.nonebot.dev/
License: MIT
Keywords: bot,feishu,larksuite
Author: StarHeartHunt
Author-email: starheart233@gmail.com
Requires-Python: >=3.9,<4.0
Classifier: Development Status :: 5 - Production/Stable
Classifier: Framework :: Robot Framework
Classifier: Framework :: Robot Framework :: Library
Classifier: License :: OSI Approved :: MIT License
Classifier: Operating System :: OS Independent
Classifier: Programming Language :: Python :: 3
Classifier: Programming Language :: Python :: 3.9
Classifier: Programming Language :: Python :: 3.10
Classifier: Programming Language :: Python :: 3.11
Classifier: Programming Language :: Python :: 3.12
Requires-Dist: cashews (>=7.0.0,<8.0.0)
Requires-Dist: nonebot2 (>=2.2.0,<3.0.0)
Requires-Dist: pycryptodome (>=3.18.0,<4.0.0)
Project-URL: Documentation, https://feishu.adapters.nonebot.dev/
Project-URL: Repository, https://github.com/nonebot/adapter-feishu
